fifa98edit/.DS_Store
fifa98edit/FifaStyles/fh00.png
fifa98edit/FifaStyles/fh01.png
fifa98edit/FifaStyles/fh02.png
fifa98edit/FifaStyles/fh03.png
fifa98edit/FifaStyles/fh04.png
fifa98edit/FifaStyles/fh05.png
fifa98edit/FifaStyles/fh06.png
fifa98edit/FifaStyles/fs00.png
fifa98edit/FifaStyles/fs01.png
fifa98edit/FifaStyles/fs02.png
fifa98edit/FifaStyles/fs03.png
fifa98edit/FifaStyles/fs04.png
fifa98edit/FifaStyles/fs05.png
fifa98edit/FifaStyles/fs06.png
fifa98edit/FifaStyles/fs07.png
fifa98edit/FifaStyles/fs08.png
fifa98edit/FifaStyles/hs00.png
fifa98edit/FifaStyles/hs01.png
fifa98edit/FifaStyles/hs02.png
fifa98edit/FifaStyles/hs03.png
fifa98edit/FifaStyles/hs04.png
fifa98edit/FifaStyles/hs05.png
fifa98edit/FifaStyles/hs06.png
fifa98edit/FifaStyles/hs07.png
fifa98edit/FifaStyles/hs08.png
fifa98edit/FifaStyles/hs09.png
fifa98edit/FifaStyles/hs10.png
fifa98edit/FifaStyles/hs11.png
fifa98edit/__init__.py
fifa98edit/average_fifa.py
fifa98edit/display_jerseys.py
fifa98edit/fifa_config.json
fifa98edit/jersey_mask.png
fifa98edit-0.1.47.dist-info/LICENSE
fifa98edit-0.1.47.dist-info/METADATA
fifa98edit-0.1.47.dist-info/WHEEL
fifa98edit-0.1.47.dist-info/RECORD
