Metadata-Version: 2.1
Name: fifa98edit
Version: 0.1.47
Summary: A command-line database editor for FIFA RTWC 98.
Home-page: https://github.com/ma-akad/fifa98edit
License: MIT
Author: Megas Alexandros
Author-email: megas_alexandros@hotmail.com
Requires-Python: >=3.8,<4.0
Classifier: License :: OSI Approved :: MIT License
Classifier: Programming Language :: Python :: 3
Classifier: Programming Language :: Python :: 3.8
Classifier: Programming Language :: Python :: 3.9
Classifier: Programming Language :: Python :: 3.10
Classifier: Programming Language :: Python :: 3.11
Requires-Dist: colored (>=1.4.4,<2.0.0) ; sys_platform == "win32"
Requires-Dist: numpy (>=1.19.0,<2.0.0)
Requires-Dist: pandas (>=1.0.5,<2.0.0)
Requires-Dist: pillow (>=7.2.0,<8.0.0)
Requires-Dist: pypiwin32 (>=223,<224) ; sys_platform == "win32"
Requires-Dist: unidecode (>=1.3.2,<2.0.0)
Project-URL: Repository, https://github.com/ma-akad/fifa98edit
